odoo/addons/hr_expense_receipt_require/README.rst
odoo/addons/hr_expense_receipt_require/__init__.py
odoo/addons/hr_expense_receipt_require/__manifest__.py
odoo/addons/hr_expense_receipt_require/i18n/hr_expense_receipt_require.pot
odoo/addons/hr_expense_receipt_require/models/__init__.py
odoo/addons/hr_expense_receipt_require/models/hr_expense.py
odoo/addons/hr_expense_receipt_require/models/product_template.py
odoo/addons/hr_expense_receipt_require/readme/CONFIGURE.rst
odoo/addons/hr_expense_receipt_require/readme/CONTRIBUTORS.rst
odoo/addons/hr_expense_receipt_require/readme/DESCRIPTION.rst
odoo/addons/hr_expense_receipt_require/readme/USAGE.rst
odoo/addons/hr_expense_receipt_require/security/security_view.xml
odoo/addons/hr_expense_receipt_require/static/description/icon.png
odoo/addons/hr_expense_receipt_require/static/description/index.html
odoo/addons/hr_expense_receipt_require/tests/__init__.py
odoo/addons/hr_expense_receipt_require/tests/test_hr_expense.py
odoo/addons/hr_expense_receipt_require/views/hr_expense_sheet_form.xml
odoo/addons/hr_expense_receipt_require/views/hr_expense_views.xml
odoo12_addon_hr_expense_receipt_require-12.0.1.0.1.dist-info/METADATA
odoo12_addon_hr_expense_receipt_require-12.0.1.0.1.dist-info/WHEEL
odoo12_addon_hr_expense_receipt_require-12.0.1.0.1.dist-info/top_level.txt
odoo12_addon_hr_expense_receipt_require-12.0.1.0.1.dist-info/RECORD
